{"intents": [
    {"tag": "greeting",
    "patterns": ["Hi","Hey", "How are you", "Is anyone there?", "Hello", "Good day"],
    "responses": ["Hello, thanks for visiting", "Good to see you again", "Hi there, how can I help?"],
    "context_set": ""
    },
    {"tag": "goodbye",
    "patterns": ["Bye", "See you later", "Goodbye"],
    "responses": ["See you later, thanks for visiting", "Have a nice day", "Bye! Come back again soon."],
    "context_set": ""
    },
    {"tag": "thanks",
    "patterns": ["Thanks", "Thank you", "That's helpful"],
    "responses": ["Happy to help!", "Any time!", "My pleasure"],
    "context_set": ""
    },
    {"tag": "hours",
    "patterns": ["What hours are you open?", "What are your hours?", "When are you open?"],
    "responses": ["We're open every day 9am-9pm", "Our hours are 9am-9pm every day"],
    "context_set": ""
    },
    {"tag": "mopeds",
    "patterns": ["Do you rent mopeds?", "Do you rent motorcycles?", "Do you rent scooters?"],
    "responses": ["We rent mopeds, motorcycles, and scooters", "Yes, we rent mopeds, motorcycles, and scooters"],
    "context_set": ""
    },
    {"tag": "payments",
    "patterns": ["Do you accept credit cards?", "Do you take Mastercard?", "Do you take VISA?"],
    "responses": ["We accept VISA, Mastercard, and American Express", "Yes, we accept credit cards"],
    "context_set": ""
    },
    {"tag": "rental",
    "patterns": ["How much does it cost to rent a moped?", "How much does it cost to rent a motorcycle?", "How much does it cost to rent a scooter?"],
    "responses": ["The cost to rent a moped is $40 per day", "The cost to rent a motorcycle is $60 per day", "The cost to rent a scooter is $30 per day"],
    "context_set": ""
    },
    {"tag": "location",
    "patterns": ["Where are you located?", "What's your address?", "Do you have a physical location?"],
    "responses": ["We are located in kathmandu Nepal", "We're located on Main Street in the center Kathmandu"],
    "context_set": ""

    }

]}